{
 "unit_id": "laneA_107",
 "practices": [
  {
   "location_id": "42d1dfe2d92fb435",
   "primary_npi": "1366788697",
   "org_npi": "1366788697",
   "name": "VETERANS SQUARE DIAGNOSTICS, INC.",
   "dba": null,
   "address": "4849 n milwaukee ave",
   "city": "CHICAGO",
   "zip": "60630",
   "phone": "(773) 577-2100",
   "ein": "474926253",
   "entity_classification": "small_group",
   "affiliated_dso": null,
   "parent_company": "CALERA CAPITAL",
   "provider_count": 2,
   "year_established": null,
   "ctx": {
    "authorized_official": "DAVID KODNER",
    "owner_reach_locations": 1,
    "owner_reach_zips": [
     "60630"
    ],
    "ein_reach_locations": 1,
    "ein_reach_zips": [
     "60630"
    ],
    "brand_hint": null,
    "institutional_hint": true,
    "has_intel_dossier": false
   },
   "_zip_city": "60630 CHICAGO"
  },
  {
   "location_id": "1cd40aac8627fec1",
   "primary_npi": "1093948697",
   "org_npi": null,
   "name": "Grzeskowiak Dental",
   "dba": null,
   "address": "5370 n milwaukee ave",
   "city": "CHICAGO",
   "zip": "60630",
   "phone": "(773) 763-6119",
   "ein": null,
   "entity_classification": "solo_established",
   "affiliated_dso": null,
   "parent_company": null,
   "provider_count": 1,
   "year_established": null,
   "ctx": {
    "authorized_official": null,
    "owner_reach_locations": 1,
    "owner_reach_zips": [
     "60630"
    ],
    "ein_reach_locations": 0,
    "ein_reach_zips": [],
    "brand_hint": null,
    "institutional_hint": false,
    "has_intel_dossier": true
   },
   "_zip_city": "60630 CHICAGO"
  },
  {
   "location_id": "f84ddcb53246f65d",
   "primary_npi": "1245671676",
   "org_npi": "1245671676",
   "name": "HASE ZAHN INC.",
   "dba": "<UNAVAIL>",
   "address": "4830 n pulaski rd",
   "city": "CHICAGO",
   "zip": "60630",
   "phone": "(773) 283-2100",
   "ein": null,
   "entity_classification": "small_group",
   "affiliated_dso": null,
   "parent_company": null,
   "provider_count": 3,
   "year_established": null,
   "ctx": {
    "authorized_official": "SIMONA BAREKET",
    "owner_reach_locations": 1,
    "owner_reach_zips": [
     "60630"
    ],
    "ein_reach_locations": 0,
    "ein_reach_zips": [],
    "brand_hint": null,
    "institutional_hint": false,
    "has_intel_dossier": false
   },
   "_zip_city": "60630 CHICAGO"
  },
  {
   "location_id": "63fb827368738619",
   "primary_npi": "1740603331",
   "org_npi": "1740603331",
   "name": "BRIGHTER SMILE LLC",
   "dba": "<UNAVAIL>",
   "address": "4845 n milwaukee ave",
   "city": "CHICAGO",
   "zip": "60630",
   "phone": "(630) 216-4544",
   "ein": null,
   "entity_classification": "solo_high_volume",
   "affiliated_dso": null,
   "parent_company": null,
   "provider_count": 1,
   "year_established": 1952,
   "ctx": {
    "authorized_official": "MICHELLE BECKERLY",
    "owner_reach_locations": 2,
    "owner_reach_zips": [
     "60563",
     "60630"
    ],
    "ein_reach_locations": 0,
    "ein_reach_zips": [],
    "brand_hint": null,
    "institutional_hint": false,
    "has_intel_dossier": false
   },
   "_zip_city": "60630 CHICAGO"
  },
  {
   "location_id": "9c28721340679749",
   "primary_npi": "1164763520",
   "org_npi": "1164763520",
   "name": "OASIS FAMILY DENTAL INC",
   "dba": null,
   "address": "5493 n milwaukee ave",
   "city": "CHICAGO",
   "zip": "60630",
   "phone": "(773) 930-4159",
   "ein": null,
   "entity_classification": "solo_established",
   "affiliated_dso": null,
   "parent_company": null,
   "provider_count": 0,
   "year_established": null,
   "ctx": {
    "authorized_official": "PAULA SKOWRONSKI-ADAMIAK",
    "owner_reach_locations": 1,
    "owner_reach_zips": [
     "60630"
    ],
    "ein_reach_locations": 0,
    "ein_reach_zips": [],
    "brand_hint": null,
    "institutional_hint": false,
    "has_intel_dossier": true
   },
   "_zip_city": "60630 CHICAGO"
  },
  {
   "location_id": "770dc428d7fe6dc3",
   "primary_npi": "1922477033",
   "org_npi": null,
   "name": "Truszkowski Dental",
   "dba": null,
   "address": "5489 n milwaukee ave",
   "city": "CHICAGO",
   "zip": "60630",
   "phone": "(773) 792-0123",
   "ein": null,
   "entity_classification": "solo_established",
   "affiliated_dso": null,
   "parent_company": null,
   "provider_count": 1,
   "year_established": null,
   "ctx": {
    "authorized_official": null,
    "owner_reach_locations": 1,
    "owner_reach_zips": [
     "60630"
    ],
    "ein_reach_locations": 0,
    "ein_reach_zips": [],
    "brand_hint": null,
    "institutional_hint": false,
    "has_intel_dossier": true
   },
   "_zip_city": "60630 CHICAGO"
  },
  {
   "location_id": "7f20eb7eeac9dae7",
   "primary_npi": "1700239464",
   "org_npi": null,
   "name": "Raoof Dental",
   "dba": null,
   "address": "5539 n monitor ave",
   "city": "CHICAGO",
   "zip": "60630",
   "phone": "(773) 417-9966",
   "ein": null,
   "entity_classification": "solo_established",
   "affiliated_dso": null,
   "parent_company": null,
   "provider_count": 1,
   "year_established": null,
   "ctx": {
    "authorized_official": null,
    "owner_reach_locations": 1,
    "owner_reach_zips": [
     "60630"
    ],
    "ein_reach_locations": 0,
    "ein_reach_zips": [],
    "brand_hint": null,
    "institutional_hint": false,
    "has_intel_dossier": false
   },
   "_zip_city": "60630 CHICAGO"
  },
  {
   "location_id": "173a37daf787f2c3",
   "primary_npi": "1215643184",
   "org_npi": "1215643184",
   "name": "AZAL DENTAL CONSULTING INC.",
   "dba": null,
   "address": "4641 w foster ave",
   "city": "CHICAGO",
   "zip": "60630",
   "phone": "(312) 607-8382",
   "ein": null,
   "entity_classification": "small_group",
   "affiliated_dso": null,
   "parent_company": null,
   "provider_count": 2,
   "year_established": null,
   "ctx": {
    "authorized_official": "SHAHVAR HUSSAIN",
    "owner_reach_locations": 2,
    "owner_reach_zips": [
     "60076",
     "60630"
    ],
    "ein_reach_locations": 0,
    "ein_reach_zips": [],
    "brand_hint": null,
    "institutional_hint": false,
    "has_intel_dossier": false
   },
   "_zip_city": "60630 CHICAGO"
  },
  {
   "location_id": "f84c9949d78fa8f2",
   "primary_npi": "1790462760",
   "org_npi": null,
   "name": "Shah Dental",
   "dba": null,
   "address": "5249 n mobile ave",
   "city": "CHICAGO",
   "zip": "60630",
   "phone": "(773) 456-7995",
   "ein": null,
   "entity_classification": "solo_established",
   "affiliated_dso": null,
   "parent_company": null,
   "provider_count": 1,
   "year_established": null,
   "ctx": {
    "authorized_official": null,
    "owner_reach_locations": 1,
    "owner_reach_zips": [
     "60630"
    ],
    "ein_reach_locations": 0,
    "ein_reach_zips": [],
    "brand_hint": null,
    "institutional_hint": false,
    "has_intel_dossier": true
   },
   "_zip_city": "60630 CHICAGO"
  },
  {
   "location_id": "b57ad8a6a5af150b",
   "primary_npi": "1477597862",
   "org_npi": null,
   "name": "Dvoracek Dental",
   "dba": null,
   "address": "6169 n nw hwy",
   "city": "CHICAGO",
   "zip": "60631",
   "phone": "(773) 792-2266",
   "ein": null,
   "entity_classification": "small_group",
   "affiliated_dso": null,
   "parent_company": null,
   "provider_count": 3,
   "year_established": null,
   "ctx": {
    "authorized_official": null,
    "owner_reach_locations": 1,
    "owner_reach_zips": [
     "60631"
    ],
    "ein_reach_locations": 0,
    "ein_reach_zips": [],
    "brand_hint": null,
    "institutional_hint": false,
    "has_intel_dossier": false
   },
   "_zip_city": "60631 CHICAGO"
  },
  {
   "location_id": "5a195c1eb06b40b4",
   "primary_npi": "1770690364",
   "org_npi": "1770690364",
   "name": "SMILE ILLINOIS LLC",
   "dba": null,
   "address": "8700 w bryn mawr ave",
   "city": "CHICAGO",
   "zip": "60631",
   "phone": "(888) 833-8441",
   "ein": "363634136",
   "entity_classification": "solo_established",
   "affiliated_dso": null,
   "parent_company": null,
   "provider_count": 1,
   "year_established": null,
   "ctx": {
    "authorized_official": "MARGO WOLL",
    "owner_reach_locations": 1,
    "owner_reach_zips": [
     "60631"
    ],
    "ein_reach_locations": 1,
    "ein_reach_zips": [
     "60631"
    ],
    "brand_hint": null,
    "institutional_hint": false,
    "has_intel_dossier": false
   },
   "_zip_city": "60631 CHICAGO"
  },
  {
   "location_id": "8c957ece2c079f8a",
   "primary_npi": "1841318805",
   "org_npi": "1841318805",
   "name": "RUSSELL J. CECALA, D.D.S., M.S., LTD DBA PERIOCARE",
   "dba": "<UNAVAIL>",
   "address": "7447 w talcott ave",
   "city": "CHICAGO",
   "zip": "60631",
   "phone": "(773) 763-5353",
   "ein": "363099822",
   "entity_classification": "large_group",
   "affiliated_dso": null,
   "parent_company": null,
   "provider_count": 5,
   "year_established": 2011,
   "ctx": {
    "authorized_official": "RUSSELL CECALA",
    "owner_reach_locations": 1,
    "owner_reach_zips": [
     "60631"
    ],
    "ein_reach_locations": 1,
    "ein_reach_zips": [
     "60631"
    ],
    "brand_hint": null,
    "institutional_hint": false,
    "has_intel_dossier": false
   },
   "_zip_city": "60631 CHICAGO"
  },
  {
   "location_id": "5341bee3458afb6d",
   "primary_npi": "1992803084",
   "org_npi": null,
   "name": "Camp Dental",
   "dba": null,
   "address": "8725 w higgins rd",
   "city": "CHICAGO",
   "zip": "60631",
   "phone": "(773) 329-4450",
   "ein": null,
   "entity_classification": "solo_established",
   "affiliated_dso": null,
   "parent_company": null,
   "provider_count": 1,
   "year_established": null,
   "ctx": {
    "authorized_official": null,
    "owner_reach_locations": 1,
    "owner_reach_zips": [
     "60631"
    ],
    "ein_reach_locations": 0,
    "ein_reach_zips": [],
    "brand_hint": null,
    "institutional_hint": false,
    "has_intel_dossier": true
   },
   "_zip_city": "60631 CHICAGO"
  },
  {
   "location_id": "9c108d65e2f04fa8",
   "primary_npi": "1487714663",
   "org_npi": null,
   "name": "Dentistry",
   "dba": null,
   "address": "6063 n nw hwy",
   "city": "CHICAGO",
   "zip": "60631",
   "phone": "(773) 763-9900",
   "ein": "363478498",
   "entity_classification": "solo_high_volume",
   "affiliated_dso": null,
   "parent_company": null,
   "provider_count": 1,
   "year_established": null,
   "ctx": {
    "authorized_official": null,
    "owner_reach_locations": 1,
    "owner_reach_zips": [
     "60631"
    ],
    "ein_reach_locations": 1,
    "ein_reach_zips": [
     "60631"
    ],
    "brand_hint": null,
    "institutional_hint": false,
    "has_intel_dossier": true
   },
   "_zip_city": "60631 CHICAGO"
  },
  {
   "location_id": "71531dc82faf156c",
   "primary_npi": "1104245950",
   "org_npi": "1104245950",
   "name": "VICTOR J. GRANDINETTI, DDS, PC",
   "dba": null,
   "address": "7215 w touhy ave",
   "city": "CHICAGO",
   "zip": "60631",
   "phone": "(773) 775-3431",
   "ein": null,
   "entity_classification": "solo_established",
   "affiliated_dso": null,
   "parent_company": null,
   "provider_count": 1,
   "year_established": null,
   "ctx": {
    "authorized_official": "TINA GRANDINETTI",
    "owner_reach_locations": 1,
    "owner_reach_zips": [
     "60631"
    ],
    "ein_reach_locations": 0,
    "ein_reach_zips": [],
    "brand_hint": null,
    "institutional_hint": false,
    "has_intel_dossier": true
   },
   "_zip_city": "60631 CHICAGO"
  },
  {
   "location_id": "0776fc56ef8a8a64",
   "primary_npi": "1699101477",
   "org_npi": "1699101477",
   "name": "KACZYNSKI DDS, P.C.",
   "dba": null,
   "address": "6075 n nw hwy",
   "city": "CHICAGO",
   "zip": "60631",
   "phone": "(773) 792-8008",
   "ein": null,
   "entity_classification": "solo_established",
   "affiliated_dso": null,
   "parent_company": null,
   "provider_count": 1,
   "year_established": null,
   "ctx": {
    "authorized_official": "THOMAS KACZYNSKI",
    "owner_reach_locations": 1,
    "owner_reach_zips": [
     "60631"
    ],
    "ein_reach_locations": 0,
    "ein_reach_zips": [],
    "brand_hint": null,
    "institutional_hint": false,
    "has_intel_dossier": false
   },
   "_zip_city": "60631 CHICAGO"
  }
 ]
}