[
 {
  "location_id": "749eed72f0e57a93",
  "practice_name": "ACCESS DENTAL CENTER",
  "normalized_address": "276 w fullerton ave",
  "city": "ADDISON",
  "zip": "60101",
  "phone": "(630) 628-8884",
  "vendor_website_hint": "Www6.Accessdentalcenter.Com",
  "provider_count": 3
 },
 {
  "location_id": "86df7d2ce7507196",
  "practice_name": "Jain Family Dental Ctr",
  "normalized_address": "33 n addison rd",
  "city": "ADDISON",
  "zip": "60101",
  "phone": "(630) 530-2224",
  "vendor_website_hint": "Jaindental.Com",
  "provider_count": 2
 },
 {
  "location_id": "86f0b24aac6e0fff",
  "practice_name": "DENTAL PROFILE 2",
  "normalized_address": "120 e lake st",
  "city": "ADDISON",
  "zip": "60101",
  "phone": "(630) 530-2498",
  "vendor_website_hint": "1stfamilydental.Com",
  "provider_count": 8
 },
 {
  "location_id": "cbd45aceeec52e53",
  "practice_name": "SRI WELLNESS CENTER",
  "normalized_address": "190 n swift rd",
  "city": "ADDISON",
  "zip": "60101",
  "phone": "(630) 627-7626",
  "vendor_website_hint": "Addisondentalil.Com",
  "provider_count": 3,
  "dba": "<UNAVAIL>"
 },
 {
  "location_id": "2c8727ed28c2a736",
  "practice_name": "ANGELA SKIDMORE DDS PC",
  "normalized_address": "988 s bartlett rd",
  "city": "BARTLETT",
  "zip": "60103",
  "phone": "(630) 289-4288",
  "vendor_website_hint": "Bartlettdentaloffice.Com",
  "provider_count": 2,
  "dba": "<UNAVAIL>"
 },
 {
  "location_id": "33e012d3f3ad214a",
  "practice_name": "Bartlett Family Dental",
  "normalized_address": "1048 norwood ln",
  "city": "BARTLETT",
  "zip": "60103",
  "phone": "(630) 830-6056",
  "vendor_website_hint": "Bartlettfamilydental.Com",
  "provider_count": 2
 }
]