[
 {
  "location_id": "2a64e9998325e877",
  "practice_name": "Fijal & Assoc",
  "normalized_address": "29 n broadway st",
  "city": "DES PLAINES",
  "zip": "60016",
  "phone": "(847) 824-5252",
  "vendor_website_hint": "Broadwayfamilydentalgroup.Com",
  "provider_count": 3
 },
 {
  "location_id": "2faa51a8ef02fcc1",
  "practice_name": "Kenny Edward J DDS",
  "normalized_address": "780 lee st",
  "city": "DES PLAINES",
  "zip": "60016",
  "phone": "(847) 827-1809",
  "vendor_website_hint": "Myfirstclasssmile.Com",
  "provider_count": 2
 },
 {
  "location_id": "4bbaac19c7ef00f9",
  "practice_name": "THE DENTAL STORE, LTD.",
  "normalized_address": "1455 e golf rd",
  "city": "DES PLAINES",
  "zip": "60016",
  "phone": "(847) 699-3370",
  "vendor_website_hint": "Roserootdental.Com",
  "provider_count": 5
 },
 {
  "location_id": "64ed9057fa6f8553",
  "practice_name": "SUBURBAN FAMILY DENTAL",
  "normalized_address": "645 w golf rd",
  "city": "DES PLAINES",
  "zip": "60016",
  "phone": "(847) 640-0778",
  "vendor_website_hint": "Suburbanfamilydental.Net",
  "provider_count": 2
 },
 {
  "location_id": "85a220a7d7130993",
  "practice_name": "BRITE BITE DENTAL, PC",
  "normalized_address": "444 lee st",
  "city": "DES PLAINES",
  "zip": "60016",
  "phone": "(847) 827-2929",
  "vendor_website_hint": "Britebitedental.Com",
  "provider_count": 2
 },
 {
  "location_id": "8adc098b0f4b51c9",
  "practice_name": "RSPATEL, INC.",
  "normalized_address": "1533 ellinwood ave",
  "city": "DES PLAINES",
  "zip": "60016",
  "phone": "(847) 297-0100",
  "vendor_website_hint": "Ajdentalcenter.Com",
  "provider_count": 3,
  "dba": "<UNAVAIL>"
 }
]